access/config/__init__.py
access/config/config.lark
access/config/esm1p6_layout_input.py
access/config/fortran_nml.py
access/config/layout_config.py
access/config/mom6_input.py
access/config/nuopc_config.py
access/config/parser.py
access/config/yaml_config.py
access_config_utils-0.1.dist-info/licenses/LICENSE
access_config_utils-0.1.dist-info/METADATA
access_config_utils-0.1.dist-info/WHEEL
access_config_utils-0.1.dist-info/top_level.txt
access_config_utils-0.1.dist-info/RECORD
