Metadata-Version: 2.4
Name: access-config-utils
Version: 0.1
Summary: Utilities to work with configurations for the ACCESS climate models.
Author-email: Micael Oliveira <micael.oliveira@anu.edu.au>
Keywords: configurations,parser,access
Classifier: License :: OSI Approved :: Apache Software License
Classifier: Operating System :: POSIX :: Linux
Classifier: Programming Language :: Python :: 3
Classifier: Topic :: Utilities
License-File: LICENSE
Requires-Dist: lark
Requires-Dist: ruamel.yaml
Provides-Extra: devel
Requires-Dist: ruff; extra == "devel"
Requires-Dist: pre-commit; extra == "devel"
Provides-Extra: test
Requires-Dist: pytest; extra == "test"
Requires-Dist: pytest-cov; extra == "test"
Dynamic: license-file
